{
  "httpMethod": "POST",
  "path": "/movePallet",
  "body": "{\"codigo\":\"PALLET12345\",\"ubicacion\":\"BODEGA\"}",
  "resource": "/movePallet",
  "pathParameters": {},
  "stageVariables": null,
  "headers": {
    "Content-Type": "application/json"
  },
  "multiValueHeaders": {
    "Content-Type": ["application/json"]
  },
  "queryStringParameters": {},
  "multiValueQueryStringParameters": null,
  "isBase64Encoded": false,
  "requestContext": {
    "resourceId": "123456",
    "resourcePath": "/movePallet",
    "httpMethod": "POST",
    "extendedRequestId": "example-id",
    "requestTime": "09/Apr/2023:12:34:56 +0000",
    "path": "/movePallet",
    "accountId": "123456789012",
    "protocol": "HTTP/1.1",
    "stage": "prod",
    "domainPrefix": "example",
    "requestTimeEpoch": 1660000000000,
    "requestId": "a1b2c3d4-5678-90ab-cdef-example",
    "identity": {
      "cognitoIdentityPoolId": null,
      "accountId": null,
      "cognitoIdentityId": null,
      "caller": null,
      "sourceIp": "127.0.0.1",
      "principalOrgId": null,
      "accessKey": null,
      "cognitoAuthenticationType": null,
      "cognitoAuthenticationProvider": null,
      "userArn": null,
      "userAgent": "Mozilla/5.0 (Windows NT 10.0; Win64; x64) AppleWebKit/537.36 (KHTML, like Gecko) Chrome/94.0.4606.81 Safari/537.36",
      "user": null
    },
    "domainName": "example.com",
    "apiId": "1234567890"
  }
} 